{"cameraMode":{"drawMode":0,"name":"Shaded","section":"Shading Mode"},"sceneLighting":true,"audioPlay":false,"sceneViewState":{"m_AlwaysRefresh":false,"showFog":true,"showSkybox":true,"showFlares":true,"showImageEffects":true,"showParticleSystems":true,"showVisualEffectGraphs":true,"m_FxEnabled":true},"in2DMode":false,"pivot":{"x":-135.8125762939453,"y":-300.6332092285156,"z":510.9111633300781},"rotation":{"x":0.22955197095870973,"y":-0.11058758944272995,"z":0.02616622857749462,"w":0.9667983651161194},"size":360.4654846191406,"orthographic":false}